pdf_auto_outline/__init__.py
pdf_auto_outline/__main__.py
pdf_auto_outline/main.py
pdf_auto_outline/test.py
pdf_auto_outline-0.1.6.dist-info/WHEEL
pdf_auto_outline-0.1.6.dist-info/entry_points.txt
pdf_auto_outline-0.1.6.dist-info/METADATA
pdf_auto_outline-0.1.6.dist-info/RECORD
