Metadata-Version: 2.3
Name: pdf-auto-outline
Version: 0.1.6
Summary: Automatically generate and edit PDF table of contents / outline
Author: Rossikos
Author-email: Rossikos <216631970+rossikos@users.noreply.github.com>
Classifier: Programming Language :: Python :: 3
Classifier: License :: OSI Approved :: GNU General Public License v3 (GPLv3)
Classifier: Operating System :: OS Independent
Requires-Dist: pymupdf-layout>=1.26.6
Requires-Dist: sioyek ; extra == 'sioyek'
Requires-Python: >=3.13
Project-URL: Bug Tracker, https://github.com/rossikos/pdf-auto-outline/issues
Project-URL: Homepage, https://github.com/rossikos/pdf-auto-outline
Provides-Extra: sioyek
